weather_mcp_pypi/__init__.py
weather_mcp_pypi-0.1.2.dist-info/METADATA
weather_mcp_pypi-0.1.2.dist-info/WHEEL
weather_mcp_pypi-0.1.2.dist-info/entry_points.txt
weather_mcp_pypi-0.1.2.dist-info/RECORD
