Metadata-Version: 2.4
Name: weather-mcp-pypi
Version: 0.1.2
Summary: Add your description here
Author-email: hancs5 <hancs5@asiainfo.com>
Requires-Python: >=3.10
Requires-Dist: mcp[cli]>=1.9.3
Requires-Dist: requests>=2.32.4
